LICENSE
README.md
setup.py
fastfinder/__init__.py
fastfinder/__version__.py
fastfinder/fastfinder_controller.py
fastfinder/thresholds.py
fastfinder.egg-info/PKG-INFO
fastfinder.egg-info/SOURCES.txt
fastfinder.egg-info/dependency_links.txt
fastfinder.egg-info/top_level.txt
fastfinder/dustmaps/__init__.py
fastfinder/dustmaps/extinction.py
fastfinder/features/__init__.py
fastfinder/features/feat_contrastor.py
fastfinder/features/lc_extractor.py
fastfinder/features/lc_modeller.py
fastfinder/features/plotter.py
fastfinder/outputs/__init__.py
logs/__init__.py